agentverse/__init__.py
agentverse/agentverse.py
agentverse/demo.py
agentverse/gui.py
agentverse/initialization.py
agentverse/logging.py
agentverse/message.py
agentverse/registry.py
agentverse/simulation.py
agentverse/tasksolving.py
agentverse/utils.py
agentverse/agents/__init__.py
agentverse/agents/base.py
agentverse/agents/simulation_agent/__init__.py
agentverse/agents/simulation_agent/conversation.py
agentverse/agents/simulation_agent/prisoner_dilemma.py
agentverse/agents/simulation_agent/reflection.py
agentverse/agents/simulation_agent/tool.py
agentverse/agents/tasksolving_agent/__init__.py
agentverse/agents/tasksolving_agent/critic.py
agentverse/agents/tasksolving_agent/evaluator.py
agentverse/agents/tasksolving_agent/executor.py
agentverse/agents/tasksolving_agent/manager.py
agentverse/agents/tasksolving_agent/role_assigner.py
agentverse/agents/tasksolving_agent/solver.py
agentverse/environments/__init__.py
agentverse/environments/base.py
agentverse/environments/simulation_env/__init__.py
agentverse/environments/simulation_env/basic.py
agentverse/environments/simulation_env/pokemon.py
agentverse/environments/simulation_env/prisoner_dilemma.py
agentverse/environments/simulation_env/reflection.py
agentverse/environments/simulation_env/sde_team.py
agentverse/environments/simulation_env/sde_team_given_tests.py
agentverse/environments/simulation_env/rules/__init__.py
agentverse/environments/simulation_env/rules/base.py
agentverse/environments/simulation_env/rules/describer/__init__.py
agentverse/environments/simulation_env/rules/describer/base.py
agentverse/environments/simulation_env/rules/describer/basic.py
agentverse/environments/simulation_env/rules/describer/classroom.py
agentverse/environments/simulation_env/rules/describer/pokemon.py
agentverse/environments/simulation_env/rules/describer/prisoner.py
agentverse/environments/simulation_env/rules/order/__init__.py
agentverse/environments/simulation_env/rules/order/base.py
agentverse-0.1.8.1.dist-info/LICENSE
agentverse-0.1.8.1.dist-info/METADATA
agentverse-0.1.8.1.dist-info/WHEEL
agentverse-0.1.8.1.dist-info/entry_points.txt
agentverse-0.1.8.1.dist-info/top_level.txt
agentverse-0.1.8.1.dist-info/RECORD
