Metadata-Version: 2.1
Name: agentverse
Version: 0.1.8.1
Summary: A versatile framework that streamlines the process of creating custom multi-agent environments for large language models (LLMs).
Home-page: https://github.com/OpenBMB/AgentVerse
Author: AgentVerse Team
Author-email: agentverse2@gmail.com
Classifier: Programming Language :: Python :: 3
Classifier: License :: OSI Approved :: Apache Software License
Classifier: Operating System :: OS Independent
Requires-Python: >=3.9
License-File: LICENSE
Requires-Dist: pyyaml
Requires-Dist: fastapi ==0.95.1
Requires-Dist: uvicorn
Requires-Dist: py3langid
Requires-Dist: iso-639
Requires-Dist: openai ==0.27.8
Requires-Dist: opencv-python ==4.8.0.76
Requires-Dist: gradio
Requires-Dist: httpx[socks] ==0.25.0
Requires-Dist: astunparse
Requires-Dist: langchain ==0.0.157
Requires-Dist: scikit-learn
Requires-Dist: pydantic ==1.10.7
Requires-Dist: typing-extensions ==4.5.0
Requires-Dist: typing-inspect ==0.8.0
Requires-Dist: colorlog
Requires-Dist: rapidfuzz
Requires-Dist: spacy
Requires-Dist: colorama ==0.4.6
Requires-Dist: fschat[model_worker,webui]
